LICENSE
MANIFEST.in
Makefile
README.md
VERSION
pyproject.toml
setup.cfg
setup.py
binarycpython/__init__.py
binarycpython.egg-info/PKG-INFO
binarycpython.egg-info/SOURCES.txt
binarycpython.egg-info/dependency_links.txt
binarycpython.egg-info/requires.txt
binarycpython.egg-info/top_level.txt
binarycpython/core/__init__.py
binarycpython/tests/extra_tests.py
binarycpython/tests/main.py
binarycpython/tests/main_with_notebooks.py
binarycpython/tests/python_API_test.py
binarycpython/tests/test_c_bindings.py
binarycpython/tests/test_custom_logging.py
binarycpython/tests/test_distributions.py
binarycpython/tests/test_functions.py
binarycpython/tests/test_grid.py
binarycpython/tests/test_grid_options_defaults.py
binarycpython/tests/test_hpc_functions.py
binarycpython/tests/test_notebooks.py
binarycpython/tests/test_plot_functions.py
binarycpython/tests/test_run_system_wrapper.py
binarycpython/tests/test_spacing_functions.py
binarycpython/tests/test_stellar_types.py
binarycpython/tests/test_useful_funcs.py
binarycpython/utils/__init__.py
binarycpython/utils/custom_logging_functions.py
binarycpython/utils/dicts.py
binarycpython/utils/distribution_functions.py
binarycpython/utils/ensemble.py
binarycpython/utils/functions.py
binarycpython/utils/grid.py
binarycpython/utils/grid_options_defaults.py
binarycpython/utils/hpc_functions.py
binarycpython/utils/moe_di_stefano_2017_data.py
binarycpython/utils/plot_functions.py
binarycpython/utils/run_system_wrapper.py
binarycpython/utils/spacing_functions.py
binarycpython/utils/stellar_types.py
binarycpython/utils/useful_funcs.py
include/binary_c_python.h
src/binary_c_python.c