Metadata-Version: 1.1
Name: binarycpython
Version: 0.9.2
Summary: This is a python API for binary_c (versions 2.1.7,2.2pre1,2.2.0,2.2.1) by David Hendriks, Rob Izzard and collaborators. Based on the initial set up by Jeff andrews.
Home-page: https://gitlab.eps.surrey.ac.uk/ri0005/binary_c-python
Author: David Hendriks
Author-email: davidhendriks93@gmail.com
License: gpl
Keywords: binary_c,astrophysics,stellar evolution,population synthesis
Platform: UNKNOWN
Classifier: Development Status :: 4 - Beta
Classifier: License :: OSI Approved :: GNU General Public License v3 or later (GPLv3+)
Classifier: Intended Audience :: Developers
Classifier: Intended Audience :: Science/Research
Classifier: Operating System :: POSIX :: Linux
Classifier: Programming Language :: Python :: 3
Classifier: Programming Language :: C
Classifier: Topic :: Education
Classifier: Topic :: Scientific/Engineering :: Physics
Classifier: Topic :: Software Development :: Libraries :: Python Modules
